MANIFEST.in
py26-requirements.txt
requirements.txt
setup.cfg
setup.py
test-requirements.txt
asynxd/__init__.py
asynxd/apis.py
asynxd/application.cfg
asynxd/engines.py
asynxd/forms.py
asynxd/manage.py
asynxd/version.txt
asynxd.egg-info/PKG-INFO
asynxd.egg-info/SOURCES.txt
asynxd.egg-info/dependency_links.txt
asynxd.egg-info/entry_points.txt
asynxd.egg-info/requires.txt
asynxd.egg-info/top_level.txt
asynxd.egg-info/zip-safe
tests/__init__.py
tests/test_apis.py
tests/test_forms.py