Metadata-Version: 1.1
Name: asynxd
Version: 0.4dev3
Summary: RESTful server side of an open source, distributed, and web / HTTP oriented taskqueue & scheduler service inspired by Google App Engine
Home-page: https://github.com/guokr/asynx
Author: Guokr
Author-email: bug@guokr.com
License: UNKNOWN
Platform: UNKNOWN
Classifier: Development Status :: 3 - Alpha
Classifier: Environment :: Web Environment
Classifier: Framework :: Flask
Classifier: Intended Audience :: Developers
Classifier: License :: OSI Approved :: MIT License
Classifier: Operating System :: POSIX
Classifier: Programming Language :: Python
Classifier: Programming Language :: Python :: 2 :: Only
Classifier: Programming Language :: Python :: 2.6
Classifier: Programming Language :: Python :: 2.7
Classifier: Topic :: Internet :: WWW/HTTP :: WSGI :: Application
